{"gtabs":[{"panes":[{"ptabs":[{"history":[{"dir":"/home/xami/awebcode","file":"..","relpos":0,"ts":1748616887},{"dir":"/home/xami","file":"dotfiles","relpos":7,"ts":1748616887},{"dir":"/home/xami/dotfiles","file":"..","relpos":0,"ts":1748616887},{"dir":"/home/xami","file":"dotfiles","relpos":7,"ts":1748616887},{"dir":"/home","file":"xami","relpos":2,"ts":1748616887},{"dir":"/home/xami","file":"fun_joke.jpg","relpos":30,"ts":1748616887},{"dir":"/home/xami/awebcode","file":"..","relpos":0,"ts":1748616887},{"dir":"/home/xami","file":"dotfiles","relpos":7,"ts":1748616887},{"dir":"/home/xami/dotfiles","file":"..","relpos":0,"ts":1748616887},{"dir":"/home/xami","file":"dotfiles","relpos":7,"ts":1748616887},{"dir":"/home","file":"xami","relpos":2,"ts":1748616887},{"dir":"/home/xami","file":"codofduty","relpos":4,"ts":1748616887},{"dir":"/home/xami/awebcode","file":"..","relpos":0,"ts":1748616887},{"dir":"/home/xami","file":"dotfiles","relpos":7,"ts":1748616887},{"dir":"/home/xami/dotfiles","file":"..","relpos":0,"ts":1748616887},{"dir":"/home/xami","file":"dotfiles","relpos":7,"ts":1748616887},{"dir":"/home","file":"xami","relpos":2,"ts":1748616887},{"dir":"/home/xami","file":"fun_joke.jpg","relpos":30,"ts":1748616887},{"dir":"/home/xami/awebcode","file":"..","relpos":0,"ts":1748616887},{"dir":"/home/xami","file":"dotfiles","relpos":7,"ts":1748616887},{"dir":"/home/xami/dotfiles","file":"..","relpos":0,"ts":1748616887},{"dir":"/home/xami","file":"dotfiles","relpos":7,"ts":1748616887},{"dir":"/home","file":"xami","relpos":2,"ts":1748616887},{"dir":"/home/xami","file":".config","relpos":3,"ts":1748616887},{"dir":"/home/xami/awebcode","file":"..","relpos":0,"ts":1748616887},{"dir":"/home/xami","file":"dotfiles","relpos":7,"ts":1748616887},{"dir":"/home/xami/dotfiles","file":"..","relpos":0,"ts":1748616887},{"dir":"/home/xami","file":"dotfiles","relpos":7,"ts":1748616887},{"dir":"/home","file":"xami","relpos":2,"ts":1748616887},{"dir":"/home/xami","file":"fun_joke.jpg","relpos":30,"ts":1748616887},{"dir":"/home/xami/awebcode","file":"..","relpos":0,"ts":1748616887},{"dir":"/home/xami","file":"dotfiles","relpos":7,"ts":1748616887},{"dir":"/home/xami/dotfiles","file":"..","relpos":0,"ts":1748616887},{"dir":"/home/xami","file":"dotfiles","relpos":7,"ts":1748616887},{"dir":"/home","file":"xami","relpos":2,"ts":1748616887},{"dir":"/home/xami","file":"codofduty","relpos":4,"ts":1748616887},{"dir":"/home/xami/codofduty","file":"cccppp","relpos":2,"ts":1748649452},{"dir":"/home/xami/codofduty/cccppp","file":"arithmetic_operator.cpp","relpos":2,"ts":1748649452},{"dir":"/home/xami/codofduty","file":"cccppp","relpos":2,"ts":1748649452},{"dir":"/home/xami/codofduty/cccppp","file":"arithmetic_operator.cpp","relpos":2,"ts":1748649452},{"dir":"/home/xami/codofduty","file":"cccppp","relpos":2,"ts":1748649452},{"dir":"/home/xami/codofduty/cccppp","file":"arithmetic_operator.cpp","relpos":2,"ts":1748649452},{"dir":"/home/xami/codofduty","file":"cccppp","relpos":2,"ts":1748649452},{"dir":"/home/xami/codofduty/cccppp","file":"arithmetic_operator.cpp","relpos":2,"ts":1748649452},{"dir":"/home/xami/.config","file":"vifm","relpos":34,"ts":1748827263},{"dir":"/home/xami","file":".tmux","relpos":14,"ts":1748827263},{"dir":"/home/xami/.tmux","file":"..","relpos":0,"ts":1748827263},{"dir":"/home/xami","file":"books","relpos":4,"ts":1748827263},{"dir":"/home/xami/books","file":"..","relpos":0,"ts":1748827263},{"dir":"/home/xami/.config","file":"vifm","relpos":34,"ts":1748827263},{"dir":"/home/xami","file":".tmux","relpos":14,"ts":1748827263},{"dir":"/home/xami/.tmux","file":"..","relpos":0,"ts":1748827263},{"dir":"/home/xami","file":"books","relpos":4,"ts":1748827263},{"dir":"/home/xami/books","file":"..","relpos":0,"ts":1748827263},{"dir":"/home/xami/.config","file":"vifm","relpos":34,"ts":1748827263},{"dir":"/home/xami","file":".tmux","relpos":14,"ts":1748827263},{"dir":"/home/xami/.tmux","file":"..","relpos":0,"ts":1748827263},{"dir":"/home/xami","file":"books","relpos":4,"ts":1748827263},{"dir":"/home/xami/books","file":"..","relpos":0,"ts":1748827263},{"dir":"/home/xami/.config","file":"vifm","relpos":34,"ts":1748827263},{"dir":"/home/xami","file":".tmux","relpos":14,"ts":1748827263},{"dir":"/home/xami/.tmux","file":"..","relpos":0,"ts":1748827263},{"dir":"/home/xami","file":"books","relpos":4,"ts":1748827263},{"dir":"/home/xami/books","file":"..","relpos":0,"ts":1748827263},{"dir":"/home/xami","file":"cheatsheet","relpos":7,"ts":1748893757},{"dir":"/home/xami/cheatsheet","file":"html-cheatsheet.md","relpos":1,"ts":1748911239},{"dir":"/home/xami","file":".myclirc","relpos":37,"ts":1748911239},{"dir":"/home/xami/cheatsheet","file":"html-cheatsheet.md","relpos":1,"ts":1748911239},{"dir":"/home/xami","file":"ziya.txt","relpos":42,"ts":1748911239},{"dir":"/home/xami/cheatsheet","file":"html-cheatsheet.md","relpos":1,"ts":1748911239},{"dir":"/home/xami","file":".myclirc","relpos":37,"ts":1748911239},{"dir":"/home/xami/cheatsheet","file":"html-cheatsheet.md","relpos":1,"ts":1748911239},{"dir":"/home/xami","file":"ziya.txt","relpos":42,"ts":1748911239},{"dir":"/home/xami/vids/restart_php/gio_php","file":"youtube video #XQ5Pd-6Hnjk [XQ5Pd-6Hnjk].mkv","relpos":41,"ts":1749156660},{"dir":"/home","file":"zephyr","relpos":1,"ts":1750242026},{"dir":"/home/zephyr","file":"office","relpos":31,"ts":1750873166},{"dir":"/home/zephyr/office","file":"..","relpos":0,"ts":1750873166},{"dir":"/home/zephyr","file":"office","relpos":31,"ts":1750873216},{"dir":"/home/zephyr/office","file":"..","relpos":0,"ts":1750873216},{"dir":"/home/zephyr","file":"zephyr","relpos":34,"ts":1750873216},{"dir":"/home/zephyr/zephyr","file":"php","relpos":3,"ts":1750873216},{"dir":"/home/zephyr/zephyr/php","file":"gio","relpos":3,"ts":1750873216},{"dir":"/home/zephyr/zephyr/php/gio","file":"index.php","relpos":1,"ts":1750873216},{"dir":"/home/zephyr","file":"zephyr","relpos":37,"ts":1750887108},{"dir":"/home/zephyr/zephyr","file":"php","relpos":3,"ts":1750887108},{"dir":"/home/zephyr/zephyr/php","file":"gio","relpos":3,"ts":1750887108},{"dir":"/home/zephyr/zephyr/php/gio","file":"..","relpos":0,"ts":1750887108},{"dir":"/home/zephyr/zephyr/php","file":"funda_of_webit","relpos":2,"ts":1750887108},{"dir":"/home/zephyr/zephyr/php/funda_of_webit","file":"..","relpos":0,"ts":1750887108},{"dir":"/home/zephyr/zephyr/php","file":"gio","relpos":3,"ts":1752447646},{"dir":"/home/zephyr/zephyr/php/gio","file":"..","relpos":0,"ts":1752447646},{"dir":"/home/zephyr/zephyr/php","file":"..","relpos":0,"ts":1752602016},{"dir":"/home/zephyr/zephyr","file":"..","relpos":0,"ts":1753703279},{"dir":"/home/zephyr","file":"Downloads","relpos":4,"ts":1753703279},{"dir":"/home/zephyr/Downloads","file":"firefoxdd","relpos":3,"ts":1753703279},{"dir":"/home/zephyr/Downloads/firefoxdd","file":"..","relpos":0,"ts":1753703279},{"dir":"/home/zephyr/Downloads","file":"..","relpos":0,"ts":1753704495},{"dir":"/home/zephyr","file":"project","relpos":14,"ts":1753704495},{"dir":"/home/zephyr/project","file":"..","relpos":0,"ts":1753704495},{"dir":"/home/zephyr","file":".viminfo","relpos":10,"ts":1753705169}],"filters":{"invert":true,"dot":false,"manual":"","auto":""},"last-location":"/home/zephyr","sorting":[2],"preview":false}]},{"ptabs":[{"history":[{"dir":"/home/xami","file":"ziya.txt","relpos":41,"ts":1748609380},{"dir":"/","file":"home","relpos":4,"ts":1748609380},{"dir":"/home","file":"xami","relpos":2,"ts":1748609380},{"dir":"/home/xami","file":"Downloads","relpos":1,"ts":1748609380},{"dir":"/","file":"home","relpos":4,"ts":1748609380},{"dir":"/home","file":"xami","relpos":2,"ts":1748609380},{"dir":"/home/xami","file":"ziya.txt","relpos":41,"ts":1748609380},{"dir":"/","file":"home","relpos":4,"ts":1748609380},{"dir":"/home","file":"xami","relpos":2,"ts":1748609380},{"dir":"/home/xami","file":"Downloads","relpos":1,"ts":1748609380},{"dir":"/","file":"home","relpos":4,"ts":1748609380},{"dir":"/home","file":"xami","relpos":2,"ts":1748609380},{"dir":"/home/xami","file":"ziya.txt","relpos":41,"ts":1748609380},{"dir":"/","file":"home","relpos":4,"ts":1748609380},{"dir":"/home","file":"xami","relpos":2,"ts":1748609380},{"dir":"/home/xami","file":"Downloads","relpos":1,"ts":1748609380},{"dir":"/","file":"home","relpos":4,"ts":1748609380},{"dir":"/home","file":"xami","relpos":2,"ts":1748609380},{"dir":"/home/xami","file":"ziya.txt","relpos":41,"ts":1748609380},{"dir":"/","file":"home","relpos":4,"ts":1748609380},{"dir":"/home","file":"xami","relpos":2,"ts":1748609380},{"dir":"/home/xami","file":"Downloads","relpos":1,"ts":1748609380},{"dir":"/","file":"home","relpos":4,"ts":1748609380},{"dir":"/home","file":"xami","relpos":2,"ts":1748609380},{"dir":"/home/xami","file":"ziya.txt","relpos":41,"ts":1748609380},{"dir":"/","file":"home","relpos":4,"ts":1748609380},{"dir":"/home","file":"xami","relpos":2,"ts":1748609380},{"dir":"/home/xami","file":"Downloads","relpos":1,"ts":1748609380},{"dir":"/","file":"home","relpos":4,"ts":1748609380},{"dir":"/home","file":"xami","relpos":2,"ts":1748609380},{"dir":"/home/xami","file":"ziya.txt","relpos":41,"ts":1748609380},{"dir":"/","file":"home","relpos":4,"ts":1748609380},{"dir":"/home","file":"xami","relpos":2,"ts":1748609380},{"dir":"/home/xami","file":"Downloads","relpos":1,"ts":1748609380},{"dir":"/","file":"home","relpos":4,"ts":1748609380},{"dir":"/home","file":"xami","relpos":2,"ts":1748609380},{"dir":"/home/xami","file":"ziya.txt","relpos":41,"ts":1748609380},{"dir":"/","file":"home","relpos":4,"ts":1748609380},{"dir":"/home","file":"xami","relpos":2,"ts":1748609380},{"dir":"/home/xami","file":"Downloads","relpos":1,"ts":1748609380},{"dir":"/","file":"home","relpos":4,"ts":1748609380},{"dir":"/home","file":"xami","relpos":2,"ts":1748609380},{"dir":"/home/xami","file":"ziya.txt","relpos":41,"ts":1748609380},{"dir":"/","file":"home","relpos":4,"ts":1748609380},{"dir":"/home","file":"xami","relpos":2,"ts":1748609380},{"dir":"/home/xami","file":"Downloads","relpos":1,"ts":1748609380},{"dir":"/","file":"home","relpos":4,"ts":1748609380},{"dir":"/home","file":"xami","relpos":2,"ts":1748609380},{"dir":"/home/xami","file":"ziya.txt","relpos":41,"ts":1748609380},{"dir":"/","file":"home","relpos":4,"ts":1748609380},{"dir":"/home","file":"xami","relpos":2,"ts":1748609380},{"dir":"/home/xami","file":"Downloads","relpos":1,"ts":1748609380},{"dir":"/","file":"home","relpos":4,"ts":1748609380},{"dir":"/home","file":"xami","relpos":2,"ts":1748609380},{"dir":"/home/xami","file":"ziya.txt","relpos":41,"ts":1748609380},{"dir":"/","file":"home","relpos":4,"ts":1748609380},{"dir":"/home","file":"xami","relpos":2,"ts":1748609380},{"dir":"/home/xami","file":"Downloads","relpos":1,"ts":1748609380},{"dir":"/","file":"home","relpos":4,"ts":1748609380},{"dir":"/home","file":"xami","relpos":2,"ts":1748609380},{"dir":"/home/xami","file":"ziya.txt","relpos":41,"ts":1748609380},{"dir":"/","file":"home","relpos":4,"ts":1748609380},{"dir":"/home","file":"xami","relpos":2,"ts":1748609380},{"dir":"/home/xami","file":"Downloads","relpos":1,"ts":1748609380},{"dir":"/","file":"home","relpos":4,"ts":1748609380},{"dir":"/home","file":"xami","relpos":2,"ts":1748609380},{"dir":"/home/xami","file":"ziya.txt","relpos":41,"ts":1748609380},{"dir":"/","file":"home","relpos":4,"ts":1748609380},{"dir":"/home","file":"xami","relpos":2,"ts":1748609380},{"dir":"/home/xami","file":"Downloads","relpos":1,"ts":1748609380},{"dir":"/","file":"home","relpos":4,"ts":1748609380},{"dir":"/home","file":"xami","relpos":2,"ts":1748609380},{"dir":"/home/xami","file":"ziya.txt","relpos":41,"ts":1748609380},{"dir":"/","file":"home","relpos":4,"ts":1748609380},{"dir":"/home","file":"xami","relpos":2,"ts":1748609380},{"dir":"/home/xami","file":"Downloads","relpos":1,"ts":1748609380},{"dir":"/","file":"home","relpos":4,"ts":1748609380},{"dir":"/home","file":"xami","relpos":2,"ts":1748609380},{"dir":"/home/xami","file":"ziya.txt","relpos":41,"ts":1748609380},{"dir":"/","file":"home","relpos":4,"ts":1748609380},{"dir":"/home","file":"xami","relpos":2,"ts":1748609380},{"dir":"/home/xami","file":"Downloads","relpos":1,"ts":1748609380},{"dir":"/","file":"home","relpos":4,"ts":1748609380},{"dir":"/home","file":"xami","relpos":2,"ts":1748609380},{"dir":"/home/xami","file":"ziya.txt","relpos":41,"ts":1748609380},{"dir":"/","file":"home","relpos":4,"ts":1748609380},{"dir":"/home","file":"xami","relpos":2,"ts":1748609380},{"dir":"/home/xami","file":"Downloads","relpos":1,"ts":1748609380},{"dir":"/home","file":"xami","relpos":2,"ts":1748609446},{"dir":"/home/xami","file":"vids","relpos":18,"ts":1748629875},{"dir":"/home/xami/vids","file":"..","relpos":0,"ts":1749144720},{"dir":"/home","file":"zephyr","relpos":1,"ts":1750242026},{"dir":"/home/zephyr","file":"all_txt","relpos":2,"ts":1750242035},{"dir":"/home/zephyr/all_txt","file":"00-keyboard-backup.conf","relpos":1,"ts":1750242035},{"dir":"/home/zephyr","file":"all_txt","relpos":2,"ts":1750242035},{"dir":"/home/zephyr/all_txt","file":"00-keyboard-backup.conf","relpos":1,"ts":1750242035},{"dir":"/home/zephyr","file":"Downloads","relpos":1,"ts":1750887108},{"dir":"/home","file":"zephyr","relpos":1,"ts":1750887108},{"dir":"/","file":"lib64","relpos":6,"ts":1750887108},{"dir":"/lib64","file":"..","relpos":0,"ts":1752746952}],"filters":{"invert":true,"dot":true,"manual":"","auto":""},"last-location":"/lib64","sorting":[2],"preview":false}]}],"active-pane":0,"preview":false,"splitter":{"pos":-1,"ratio":0.5,"orientation":"v","expanded":false}}],"active-gtab":0,"trash":[{"trashed":"/home/xami/.local/share/vifm/Trash/000_🔥 PHP Full Course 2025 - Learn PHP from Scratch ｜ PHP Tutorial for Beginners 🚀 [l4_Vn-sTBL8].f251.webm.part","original":"/home/xami/vids/🔥 PHP Full Course 2025 - Learn PHP from Scratch ｜ PHP Tutorial for Beginners 🚀 [l4_Vn-sTBL8].f251.webm.part"},{"trashed":"/home/zephyr/.local/share/vifm/Trash/000_99c360f3dcd58fd08a061184e8de9979.jpg","original":"/home/zephyr/Downloads/firefoxdd/99c360f3dcd58fd08a061184e8de9979.jpg"},{"trashed":"/home/zephyr/.local/share/vifm/Trash/000_New Project(1).psd","original":"/home/zephyr/Downloads/firefoxdd/New Project(1).psd"},{"trashed":"/home/zephyr/.local/share/vifm/Trash/000_New Project(2)(1)(1).psd","original":"/home/zephyr/Downloads/firefoxdd/New Project(2)(1)(1).psd"},{"trashed":"/home/zephyr/.local/share/vifm/Trash/000_New Project(2)(1).psd","original":"/home/zephyr/Downloads/firefoxdd/New Project(2)(1).psd"},{"trashed":"/home/zephyr/.local/share/vifm/Trash/000_New Project(2).psd","original":"/home/zephyr/Downloads/firefoxdd/New Project(2).psd"},{"trashed":"/home/zephyr/.local/share/vifm/Trash/000_New Project.jpg","original":"/home/zephyr/Downloads/firefoxdd/New Project.jpg"},{"trashed":"/home/zephyr/.local/share/vifm/Trash/000_New Project.psd","original":"/home/zephyr/Downloads/firefoxdd/New Project.psd"},{"trashed":"/home/zephyr/.local/share/vifm/Trash/000_end.jpg","original":"/home/zephyr/Downloads/firefoxdd/end.jpg"},{"trashed":"/home/zephyr/.local/share/vifm/Trash/000_end_8.jpg","original":"/home/zephyr/Downloads/firefoxdd/end_8.jpg"},{"trashed":"/home/zephyr/.local/share/vifm/Trash/000_hashim.jpg","original":"/home/zephyr/Downloads/firefoxdd/hashim.jpg"},{"trashed":"/home/zephyr/.local/share/vifm/Trash/000_hashim.psd","original":"/home/zephyr/Downloads/firefoxdd/hashim.psd"},{"trashed":"/home/zephyr/.local/share/vifm/Trash/000_ms-m-s-letter-logo-design-initial-letter-ms-linked-circle-uppercase-monogram-logo-red-and-blue-ms-logo-m-s-design-ms-m-s-vector-removebg-preview.png","original":"/home/zephyr/Downloads/firefoxdd/ms-m-s-letter-logo-design-initial-letter-ms-linked-circle-uppercase-monogram-logo-red-and-blue-ms-logo-m-s-design-ms-m-s-vector-removebg-preview.png"},{"trashed":"/home/zephyr/.local/share/vifm/Trash/000_pinterestdownloader.com-1753521134.216819.jpg","original":"/home/zephyr/Downloads/firefoxdd/pinterestdownloader.com-1753521134.216819.jpg"}],"marks":{"f":{"dir":"/home/xami/zephyr/php/funda_of_webit/pos_system_in_php/admin","file":"..","ts":1748567341},"h":{"dir":"/home/zephyr/","file":"..","ts":1750242020}},"bmarks":{},"cmd-hist":[{"text":"colorscheme Default","ts":1748561745},{"text":"colo Default-256","ts":1748561745},{"text":"set numbers","ts":1748562566},{"text":"set incsearch","ts":1748565122},{"text":"%s/mpv","ts":1748565320},{"text":"%s/mpv/nn/g","ts":1748565320},{"text":"n","ts":1748566264},{"text":"shell","ts":1748568414},{"text":"cd","ts":1748602517},{"text":"!terminal","ts":1748602960},{"text":"tabclose","ts":1748602960},{"text":";q","ts":1748605666},{"text":"Q","ts":1748606175},{"text":"help autocmd","ts":1748607059},{"text":"exih","ts":1748610417},{"text":"set number","ts":1748611752},{"text":"set relativenumber","ts":1748611752},{"text":"marks","ts":1748611752},{"text":":q","ts":1748611752},{"text":"set nonumber","ts":1748911202},{"text":"set norelativenumber","ts":1748911202},{"text":"wq","ts":1749144720},{"text":"file","ts":1752447646},{"text":"Ex","ts":1752447646},{"text":"scree","ts":1752447646},{"text":"execute","ts":1752447646},{"text":"cabbrev","ts":1752447646},{"text":"help","ts":1752602016},{"text":"help vifm-c_Es","ts":1752602016},{"text":"rename laces","ts":1753703279},{"text":"diff","ts":1753703279},{"text":"rename laces.jpg","ts":1753703279},{"text":"rename l","ts":1753703279},{"text":"rename boy.jpg","ts":1753703279},{"text":"W","ts":1753703279},{"text":"rename ","ts":1753704202},{"text":"rename icon.jpg","ts":1753704202},{"text":"q","ts":1753704202}],"search-hist":[{"text":"pix","ts":1748562566},{"text":"make tmux look","ts":1748565122},{"text":"python","ts":1748565149},{"text":"mpv","ts":1748565320},{"text":"pa","ts":1748566144},{"text":"pac","ts":1748569626},{"text":"/jl","ts":1748602487},{"text":".loc","ts":1748602960},{"text":".config","ts":1748602960},{"text":"nv","ts":1748602960},{"text":"all","ts":1748602960},{"text":"vif","ts":1748606173},{"text":".tm","ts":1748827263},{"text":"book","ts":1748827263},{"text":"vi","ts":1749144720},{"text":"ze","ts":1750887108},{"text":"dow","ts":1753703279},{"text":"pr","ts":1753704495},{"text":"pro","ts":1753705169}],"prompt-hist":[{"text":"live.ttt","ts":1748602960}],"menu-cmd-hist":[{"text":"w","ts":1748602960},{"text":"q","ts":1748602960}],"regs":{"\"":["/home/zephyr/.local/share/vifm/Trash/000_New Project(1).psd","/home/zephyr/.local/share/vifm/Trash/000_New Project(2)(1)(1).psd"]},"dir-stack":[],"use-term-multiplexer":false}